nr_common_metadata_model_builder/__init__.py
nr_common_metadata_model_builder/models/__init__.py
nr_common_metadata_model_builder/models/nr_common_metadata.yaml
nr_common_metadata_model_builder/models/nr_common_metadata_model.yaml
nr_common_metadata_model_builder-4.0.0.dev15.dist-info/METADATA
nr_common_metadata_model_builder-4.0.0.dev15.dist-info/WHEEL
nr_common_metadata_model_builder-4.0.0.dev15.dist-info/entry_points.txt
nr_common_metadata_model_builder-4.0.0.dev15.dist-info/top_level.txt
nr_common_metadata_model_builder-4.0.0.dev15.dist-info/RECORD
